simplx/__init__.py
simplx/main.py
simplx-0.0.1.dist-info/LICENSE
simplx-0.0.1.dist-info/METADATA
simplx-0.0.1.dist-info/WHEEL
simplx-0.0.1.dist-info/RECORD
