Metadata-Version: 2.1
Name: simplx
Version: 0.0.1
Summary: simple programming language for typesetting
Home-page: https://github.com/fanyf22/simplx
License: BSD-3-Clause
Keywords: latex,parsing,language
Author: Philip Fan
Author-email: topfyf@qq.com
Requires-Python: >=3.12,<4.0
Classifier: Development Status :: 1 - Planning
Classifier: Environment :: Console
Classifier: Intended Audience :: Developers
Classifier: Intended Audience :: Science/Research
Classifier: License :: OSI Approved :: BSD License
Classifier: Operating System :: OS Independent
Classifier: Programming Language :: Python :: 3
Classifier: Programming Language :: Python :: 3.12
Classifier: Programming Language :: Python :: 3 :: Only
Classifier: Topic :: Software Development :: Compilers
Project-URL: Documentation, https://fanyf22.github.io/simplx
Project-URL: Repository, https://github.com/fanyf22/simplx
